pytweeper/__init__.py
pytweeper/__version__.py
pytweeper/drive.py
pytweeper/main.py
pytweeper/operation.py
pytweeper/tweeper.py
pytweeper/twitter.py
pytweeper-1.0.8.dist-info/METADATA
pytweeper-1.0.8.dist-info/WHEEL
pytweeper-1.0.8.dist-info/entry_points.txt
pytweeper-1.0.8.dist-info/top_level.txt
pytweeper-1.0.8.dist-info/RECORD
