Metadata-Version: 2.1
Name: pytweeper
Version: 1.0.8
Summary: Twitter API automated cli
Home-page: UNKNOWN
Author: Thanawat Petchuen
Author-email: thanawat1petchuen@gmail.com
License: MIT
Platform: UNKNOWN
Classifier: License :: OSI Approved :: MIT License
Classifier: Programming Language :: Python
Classifier: Programming Language :: Python :: 3
Classifier: Programming Language :: Python :: 3.6
Classifier: Programming Language :: Python :: Implementation :: CPython
Classifier: Programming Language :: Python :: Implementation :: PyPy
Requires-Python: >=3.6.0
Requires-Dist: tweepy
Requires-Dist: requests
Requires-Dist: requests-oauthlib
Requires-Dist: progress
Requires-Dist: google-api-python-client
Requires-Dist: google-auth-httplib2
Requires-Dist: google-auth-oauthlib
